{"name":"PoliciaMilitarSC","attributes":[{"nome":null},{"dt_nascimento":" 14\/04\/1981"},{"dt_desaparecimento":""},{"cidade":""},{"estado":""},{"imagem":"http:\/\/www.pm.sc.gov.br\/fmanager\/pmsc\/cadastro_desaparecidos\/des_dd_fotos11960_1.jpg"},{"fonte":"http:\/\/www.pm.sc.gov.br\/desaparecidos\/consulta-desaparecidos.php?&p_init=9"},{"circunstancia_desaparecimento":" \r\n\r\nSegundo comunicante o mesmo n\u00e3o apareceu no trabalho, desde a data mencionada, morava na regi\u00e3o do norte da ilha."},{"situacao":"desaparecida"}]}